ictiopy/fast_excel.py
ictiopy/ictiopy.py
ictiopy-1.0.0.dist-info/LICENSE
ictiopy-1.0.0.dist-info/METADATA
ictiopy-1.0.0.dist-info/WHEEL
ictiopy-1.0.0.dist-info/top_level.txt
ictiopy-1.0.0.dist-info/RECORD
