Metadata-Version: 2.1
Name: ictiopy
Version: 1.0.0
Summary: Parse observations from ictio.org's Citizen Observatory
Home-page: https://github.com/ScienceForChange/IctioPy
Author: Alex Amo (Science for Change) and Ana Álvarez (ICM-CSIC)
Author-email: alex.amo@scienceforchange.eu
License: EUPL1.2
Platform: UNKNOWN
Classifier: License :: OSI Approved :: European Union Public Licence 1.2 (EUPL 1.2)
Classifier: Programming Language :: Python :: 3
Classifier: Programming Language :: Python :: 3.7
Classifier: Development Status :: 4 - Beta
License-File: LICENSE
Requires-Dist: openpyxl
Requires-Dist: pandas
Requires-Dist: numpy
